LICENSE.txt
MANIFEST.in
README.txt
setup.py
funcaptcha/__init__.py
funcaptcha.egg-info/PKG-INFO
funcaptcha.egg-info/SOURCES.txt
funcaptcha.egg-info/dependency_links.txt
funcaptcha.egg-info/requires.txt
funcaptcha.egg-info/top_level.txt