Metadata-Version: 2.1
Name: funcaptcha
Version: 0.1.2
Summary: Funcaptcha API
Home-page: https://pypi.org/project/funcaptcha/
Author: Tekky
Author-email: xtekky@protonmail.com
License: MIT
Platform: UNKNOWN
License-File: LICENSE.txt
